n8nControl/__init__.py
n8nControl/app.py
n8nControl/n8nManagement.py
n8nControl/response/__init__.py
n8nControl/response/appResponse.py
n8ncontrol-1.7.9.dist-info/METADATA
n8ncontrol-1.7.9.dist-info/WHEEL
n8ncontrol-1.7.9.dist-info/entry_points.txt
n8ncontrol-1.7.9.dist-info/top_level.txt
n8ncontrol-1.7.9.dist-info/RECORD
