Metadata-Version: 2.4
Name: n8nControl
Version: 1.7.9
Summary: Python agent to control remote n8n instances
Author: LEV
Author-email: you@example.com
Classifier: Programming Language :: Python :: 3
Classifier: Operating System :: OS Independent
Requires-Python: >=3.8
Requires-Dist: fastapi
Requires-Dist: uvicorn
Requires-Dist: pydantic
Requires-Dist: pydantic-settings
Requires-Dist: requests
Requires-Dist: python-dotenv
Requires-Dist: python-multipart
Dynamic: author
Dynamic: author-email
Dynamic: classifier
Dynamic: requires-dist
Dynamic: requires-python
Dynamic: summary
